Metadata-Version: 1.0
Name: shero-first-package
Version: 1.0.0
Summary: My package
Home-page: UNKNOWN
Author: shero
Author-email: 2390378545@qq.com
License: UNKNOWN
Platform: UNKNOWN
